autogluon.features-1.4.0-py3.9-nspkg.pth
autogluon/features/__init__.py
autogluon/features/binning.py
autogluon/features/utils.py
autogluon/features/vectorizers.py
autogluon/features/version.py
autogluon/features/generators/__init__.py
autogluon/features/generators/abstract.py
autogluon/features/generators/astype.py
autogluon/features/generators/auto_ml_pipeline.py
autogluon/features/generators/binned.py
autogluon/features/generators/bulk.py
autogluon/features/generators/category.py
autogluon/features/generators/datetime.py
autogluon/features/generators/drop_duplicates.py
autogluon/features/generators/drop_unique.py
autogluon/features/generators/dummy.py
autogluon/features/generators/fillna.py
autogluon/features/generators/identity.py
autogluon/features/generators/isnan.py
autogluon/features/generators/label_encoder.py
autogluon/features/generators/memory_minimize.py
autogluon/features/generators/one_hot_encoder.py
autogluon/features/generators/pipeline.py
autogluon/features/generators/rename.py
autogluon/features/generators/text_ngram.py
autogluon/features/generators/text_special.py
autogluon.features-1.4.0.dist-info/LICENSE
autogluon.features-1.4.0.dist-info/METADATA
autogluon.features-1.4.0.dist-info/NOTICE
autogluon.features-1.4.0.dist-info/WHEEL
autogluon.features-1.4.0.dist-info/namespace_packages.txt
autogluon.features-1.4.0.dist-info/top_level.txt
autogluon.features-1.4.0.dist-info/zip-safe
autogluon.features-1.4.0.dist-info/RECORD
